env_switcher/__init__.py
env_switcher/env_switcher.py
darwin_env_selector-0.1.0.dist-info/LICENSE
darwin_env_selector-0.1.0.dist-info/METADATA
darwin_env_selector-0.1.0.dist-info/WHEEL
darwin_env_selector-0.1.0.dist-info/entry_points.txt
darwin_env_selector-0.1.0.dist-info/RECORD
